yaml_extender/__init__.py
yaml_extender/__main__.py
yaml_extender/cli.py
yaml_extender/logger.py
yaml_extender/xyml_exception.py
yaml_extender/xyml_file.py
yaml_extender/yaml_loader.py
yaml_extender/resolver/__init__.py
yaml_extender/resolver/include_resolver.py
yaml_extender/resolver/inline_loop_resolver.py
yaml_extender/resolver/loop_resolver.py
yaml_extender/resolver/reference_resolver.py
yaml_extender/resolver/resolver.py
yaml_extender-0.3.2.dist-info/LICENSE
yaml_extender-0.3.2.dist-info/METADATA
yaml_extender-0.3.2.dist-info/WHEEL
yaml_extender-0.3.2.dist-info/entry_points.txt
yaml_extender-0.3.2.dist-info/top_level.txt
yaml_extender-0.3.2.dist-info/RECORD
