Metadata-Version: 2.1
Name: yaml-extender
Version: 0.3.2
Summary: Extends the common .yaml syntax to provide more complex configuration options
Author-email: Simon Gallitscher <adun.sg@gmx.de>
License: BSD 3-Clause License
Project-URL: homepage, https://github.com/AdunSG/yaml-extender
Keywords: yaml,configuration,extension
Classifier: License :: OSI Approved :: BSD License
Classifier: Programming Language :: Python
Classifier: Programming Language :: Python :: 3
License-File: LICENSE
Requires-Dist: pyyaml
Provides-Extra: dev
Requires-Dist: coverage ; extra == 'dev'
Requires-Dist: pytest ; extra == 'dev'
